label_studio_anoter/__init__.py
label_studio_anoter/label_studio_anoter.py
label_studio_anoter/logger.py
label_studio_anoter-1.3.dist-info/licenses/LICENSE
label_studio_anoter-1.3.dist-info/METADATA
label_studio_anoter-1.3.dist-info/WHEEL
label_studio_anoter-1.3.dist-info/top_level.txt
label_studio_anoter-1.3.dist-info/RECORD
