Metadata-Version: 2.4
Name: label_studio_anoter
Version: 1.3
Author-email: Naseem AP <naseem@eternalrobotics.com>, Naseem AP <naseemalassampattil@gmail.com>
Maintainer-email: Naseem AP <naseemalassampattil@gmail.com>
Keywords: label_studio,label_studio_anoter,label_studio_yolo,yolo,pre_annotation,label_studio_pre_annotation
Classifier: Development Status :: 5 - Production/Stable
Classifier: Intended Audience :: Developers
Classifier: Intended Audience :: Education
Classifier: Intended Audience :: Science/Research
Classifier: License :: OSI Approved :: MIT License
Classifier: Programming Language :: Python :: 3.10
Classifier: Topic :: Software Development
Classifier: Topic :: Scientific/Engineering
Classifier: Topic :: Scientific/Engineering :: Artificial Intelligence
Classifier: Topic :: Scientific/Engineering :: Image Recognition
Classifier: Operating System :: POSIX :: Linux
Requires-Python: >=3.10
License-File: LICENSE
Requires-Dist: label-studio-sdk>=2.0.16
Requires-Dist: ultralytics>=8.3.248
Requires-Dist: Pillow>=12.1.0
Requires-Dist: tqdm>=4.67.1
Requires-Dist: requests>=2.32.5
Dynamic: license-file
